{".class":"MypyFile","_fullname":"psycopg_pool.sched","future_import_flags":["annotations"],"is_partial_stub_package":false,"is_stub":false,"names":{".class":"SymbolTable","Any":{".class":"SymbolTableNode","cross_ref":"typing.Any","kind":"Gdef"},"CLIENT_EXCEPTIONS":{".class":"SymbolTableNode","kind":"Gdef","node":{".class":"TypeAlias","alias_tvars":[],"fullname":"psycopg_pool.sched.CLIENT_EXCEPTIONS","module":"psycopg_pool.sched","no_args":true,"normalized":false,"python_3_12_type_alias":false,"target":"builtins.Exception"}},"Callable":{".class":"SymbolTableNode","cross_ref":"typing.Callable","kind":"Gdef"},"Event":{".class":"SymbolTableNode","cross_ref":"psycopg_pool._acompat.Event","kind":"Gdef"},"Lock":{".class":"SymbolTableNode","cross_ref":"psycopg_pool._acompat.Lock","kind":"Gdef"},"Scheduler":{".class":"SymbolTableNode","kind":"Gdef","node":{".class":"TypeInfo","_promote":[],"abstract_attributes":[],"alt_promote":null,"bases":["builtins.object"],"dataclass_transform_spec":null,"declared_metaclass":null,"defn":{".class":"ClassDef","fullname":"psycopg_pool.sched.Scheduler","name":"Scheduler","type_vars":[]},"deletable_attributes":[],"deprecated":null,"flags":[],"fullname":"psycopg_pool.sched.Scheduler","has_param_spec_type":false,"metaclass_type":null,"metadata":{},"module_name":"psycopg_pool.sched","mro":["psycopg_pool.sched.Scheduler","builtins.object"],"names":{".class":"SymbolTable","EMPTY_QUEUE_TIMEOUT":{".class":"SymbolTableNode","kind":"Mdef","node":{".class":"Var","flags":["is_initialized_in_class","is_ready","is_inferred","has_explicit_value"],"fullname":"psycopg_pool.sched.Scheduler.EMPTY_QUEUE_TIMEOUT","name":"EMPTY_QUEUE_TIMEOUT","setter_type":null,"type":"builtins.float"}},"__init__":{".class":"SymbolTableNode","kind":"Mdef","node":{".class":"FuncDef","abstract_status":0,"arg_kinds":[0],"arg_names":["self"],"dataclass_transform_spec":null,"deprecated":null,"flags":["is_trivial_self"],"fullname":"psycopg_pool.sched.Scheduler.__init__","name":"__init__","original_first_arg":"self","type":{".class":"CallableType","arg_kinds":[0],"arg_names":["self"],"arg_types":["psycopg_pool.sched.Scheduler"],"fallback":"builtins.function","from_concatenate":false,"implicit":false,"imprecise_arg_kinds":false,"is_bound":false,"is_ellipsis_args":false,"name":"__init__ of Scheduler","ret_type":{".class":"NoneType"},"type_guard":null,"type_is":null,"unpack_kwargs":false,"variables":[]}}},"_event":{".class":"SymbolTableNode","implicit":true,"kind":"Mdef","node":{".class":"Var","flags":["is_ready","is_inferred"],"fullname":"psycopg_pool.sched.Scheduler._event","name":"_event","setter_type":null,"type":"threading.Event"}},"_lock":{".class":"SymbolTableNode","implicit":true,"kind":"Mdef","node":{".class":"Var","flags":["is_ready","is_inferred"],"fullname":"psycopg_pool.sched.Scheduler._lock","name":"_lock","setter_type":null,"type":"_thread.RLock"}},"_queue":{".class":"SymbolTableNode","implicit":true,"kind":"Mdef","node":{".class":"Var","flags":["explicit_self_type","is_ready","is_inferred"],"fullname":"psycopg_pool.sched.Scheduler._queue","name":"_queue","setter_type":null,"type":{".class":"Instance","args":["psycopg_pool._task.Task"],"extra_attrs":null,"type_ref":"builtins.list"}}},"enter":{".class":"SymbolTableNode","kind":"Mdef","node":{".class":"FuncDef","abstract_status":0,"arg_kinds":[0,0,0],"arg_names":["self","delay","action"],"dataclass_transform_spec":null,"deprecated":null,"flags":["is_trivial_self"],"fullname":"psycopg_pool.sched.Scheduler.enter","name":"enter","original_first_arg":"self","type":{".class":"CallableType","arg_kinds":[0,0,0],"arg_names":["self","delay","action"],"arg_types":["psycopg_pool.sched.Scheduler","builtins.float",{".class":"UnionType","items":[{".class":"CallableType","arg_kinds":[],"arg_names":[],"arg_types":[],"fallback":"builtins.function","from_concatenate":false,"implicit":false,"imprecise_arg_kinds":false,"is_bound":false,"is_ellipsis_args":false,"name":null,"ret_type":{".class":"AnyType","missing_import_name":null,"source_any":null,"type_of_any":2},"type_guard":null,"type_is":null,"unpack_kwargs":false,"variables":[]},{".class":"NoneType"}],"uses_pep604_syntax":true}],"fallback":"builtins.function","from_concatenate":false,"implicit":false,"imprecise_arg_kinds":false,"is_bound":false,"is_ellipsis_args":false,"name":"enter of Scheduler","ret_type":"psycopg_pool._task.Task","type_guard":null,"type_is":null,"unpack_kwargs":false,"variables":[]}}},"enterabs":{".class":"SymbolTableNode","kind":"Mdef","node":{".class":"FuncDef","abstract_status":0,"arg_kinds":[0,0,0],"arg_names":["self","time","action"],"dataclass_transform_spec":null,"deprecated":null,"flags":["is_trivial_self"],"fullname":"psycopg_pool.sched.Scheduler.enterabs","name":"enterabs","original_first_arg":"self","type":{".class":"CallableType","arg_kinds":[0,0,0],"arg_names":["self","time","action"],"arg_types":["psycopg_pool.sched.Scheduler","builtins.float",{".class":"UnionType","items":[{".class":"CallableType","arg_kinds":[],"arg_names":[],"arg_types":[],"fallback":"builtins.function","from_concatenate":false,"implicit":false,"imprecise_arg_kinds":false,"is_bound":false,"is_ellipsis_args":false,"name":null,"ret_type":{".class":"AnyType","missing_import_name":null,"source_any":null,"type_of_any":2},"type_guard":null,"type_is":null,"unpack_kwargs":false,"variables":[]},{".class":"NoneType"}],"uses_pep604_syntax":true}],"fallback":"builtins.function","from_concatenate":false,"implicit":false,"imprecise_arg_kinds":false,"is_bound":false,"is_ellipsis_args":false,"name":"enterabs of Scheduler","ret_type":"psycopg_pool._task.Task","type_guard":null,"type_is":null,"unpack_kwargs":false,"variables":[]}}},"run":{".class":"SymbolTableNode","kind":"Mdef","node":{".class":"FuncDef","abstract_status":0,"arg_kinds":[0],"arg_names":["self"],"dataclass_transform_spec":null,"deprecated":null,"flags":["is_trivial_self"],"fullname":"psycopg_pool.sched.Scheduler.run","name":"run","original_first_arg":"self","type":{".class":"CallableType","arg_kinds":[0],"arg_names":["self"],"arg_types":["psycopg_pool.sched.Scheduler"],"fallback":"builtins.function","from_concatenate":false,"implicit":false,"imprecise_arg_kinds":false,"is_bound":false,"is_ellipsis_args":false,"name":"run of Scheduler","ret_type":{".class":"NoneType"},"type_guard":null,"type_is":null,"unpack_kwargs":false,"variables":[]}}}},"self_type":{".class":"TypeVarType","default":{".class":"AnyType","missing_import_name":null,"source_any":null,"type_of_any":4},"fullname":"psycopg_pool.sched.Scheduler.Self","id":0,"name":"Self","namespace":"","upper_bound":"psycopg_pool.sched.Scheduler","values":[],"variance":0},"slots":null,"tuple_type":null,"type_vars":[],"typeddict_type":null}},"Task":{".class":"SymbolTableNode","cross_ref":"psycopg_pool._task.Task","kind":"Gdef"},"__annotations__":{".class":"SymbolTableNode","kind":"Gdef","node":{".class":"Var","flags":["is_ready"],"fullname":"psycopg_pool.sched.__annotations__","name":"__annotations__","setter_type":null,"type":{".class":"Instance","args":["builtins.str",{".class":"AnyType","missing_import_name":null,"source_any":null,"type_of_any":6}],"extra_attrs":null,"type_ref":"builtins.dict"}}},"__doc__":{".class":"SymbolTableNode","kind":"Gdef","node":{".class":"Var","flags":["is_ready"],"fullname":"psycopg_pool.sched.__doc__","name":"__doc__","setter_type":null,"type":"builtins.str"}},"__file__":{".class":"SymbolTableNode","kind":"Gdef","node":{".class":"Var","flags":["is_ready"],"fullname":"psycopg_pool.sched.__file__","name":"__file__","setter_type":null,"type":"builtins.str"}},"__name__":{".class":"SymbolTableNode","kind":"Gdef","node":{".class":"Var","flags":["is_ready"],"fullname":"psycopg_pool.sched.__name__","name":"__name__","setter_type":null,"type":"builtins.str"}},"__package__":{".class":"SymbolTableNode","kind":"Gdef","node":{".class":"Var","flags":["is_ready"],"fullname":"psycopg_pool.sched.__package__","name":"__package__","setter_type":null,"type":"builtins.str"}},"__spec__":{".class":"SymbolTableNode","kind":"Gdef","node":{".class":"Var","flags":["is_ready"],"fullname":"psycopg_pool.sched.__spec__","name":"__spec__","setter_type":null,"type":"_frozen_importlib.ModuleSpec"}},"annotations":{".class":"SymbolTableNode","cross_ref":"__future__.annotations","kind":"Gdef"},"heappop":{".class":"SymbolTableNode","cross_ref":"_heapq.heappop","kind":"Gdef"},"heappush":{".class":"SymbolTableNode","cross_ref":"_heapq.heappush","kind":"Gdef"},"logger":{".class":"SymbolTableNode","kind":"Gdef","node":{".class":"Var","flags":["is_ready","is_inferred","has_explicit_value"],"fullname":"psycopg_pool.sched.logger","name":"logger","setter_type":null,"type":"logging.Logger"}},"logging":{".class":"SymbolTableNode","cross_ref":"logging","kind":"Gdef"},"monotonic":{".class":"SymbolTableNode","cross_ref":"time.monotonic","kind":"Gdef"}},"path":"C:\\Users\\bourn\\AppData\\Local\\Programs\\Python\\Python314\\Lib\\site-packages\\psycopg_pool\\sched.py"}